avcuda
