Metadata-Version: 2.1
Name: avcuda
Version: 0.2.4
Summary: PyAV extension with hardware encoding/decoding support on Nvidia GPUs.
Author: Matteo Destro
License: MIT License
Project-URL: Homepage, https://github.com/materight/PyAV-CUDA.git
Project-URL: Repository, https://github.com/materight/PyAV-CUDA.git
Keywords: av,cuda,torch,ffmpeg,libav,video
Classifier: Programming Language :: Python :: 3
Classifier: License :: OSI Approved :: MIT License
Classifier: Operating System :: OS Independent
License-File: LICENSE
Requires-Dist: av>=12.3.0
Requires-Dist: torch
Requires-Dist: nvidia-npp-cu12==12.3.1.54
